<?xml version="1.0" encoding="UTF-8"?>
<window id="1134">
    <defaultcontrol always="true">9001</defaultcontrol>
    <backgroundcolor>Background</backgroundcolor>
    <onunload>CancelAlarm(SwitchRight,silent)</onunload>
    <controls>
        <control type="grouplist" id="9000">
            <orientation>horizontal</orientation>
            <width>100%</width>
            <height>100%</height>
            <itemgap>0</itemgap>
            <onleft>noop</onleft>
            <onright>Close</onright>
            <control type="button" id="9001">
                <onleft>noop</onleft>
                <width>1920</width>
                <height>1080</height>
                <onfocus>AlarmClock(SwitchRight,Action(Right),00:05,silent)</onfocus>
                <onclick>Action(Right)</onclick>
                <texturefocus>special://skin/tvpmc/news/01news.jpg</texturefocus>
                <texturenofocus>special://skin/tvpmc/news/01news.jpg</texturenofocus>
            </control>
            <control type="button" id="9002">
                <width>1920</width>
                <height>1080</height>
                <onfocus>AlarmClock(SwitchRight,Action(Right),00:05,silent)</onfocus>
                <onclick>Action(Right)</onclick>
                <texturefocus>special://skin/tvpmc/news/02news.jpg</texturefocus>
                <texturenofocus>special://skin/tvpmc/news/02news.jpg</texturenofocus>
            </control>
            <control type="button" id="9003">
                <width>1920</width>
                <height>1080</height>
                <onfocus>AlarmClock(SwitchRight,Action(Right),00:05,silent)</onfocus>
                <onclick>Action(Right)</onclick>
                <texturefocus>special://skin/tvpmc/news/03news.jpg</texturefocus>
                <texturenofocus>special://skin/tvpmc/news/03news.jpg</texturenofocus>
            </control>
            <control type="button" id="9004">
                <width>1920</width>
                <height>1080</height>
                <onfocus>AlarmClock(SwitchRight,Action(Right),00:05,silent)</onfocus>
                <onclick>Action(Right)</onclick>
                <texturefocus>special://skin/tvpmc/news/04news.jpg</texturefocus>
                <texturenofocus>special://skin/tvpmc/news/04news.jpg</texturenofocus>
            </control>
            <control type="button" id="9005">
                <width>1920</width>
                <height>1080</height>
                <onfocus>AlarmClock(SwitchRight,Action(Right),00:05,silent)</onfocus>
                <onclick>Action(Right)</onclick>
                <texturefocus>special://skin/tvpmc/news/05news.jpg</texturefocus>
                <texturenofocus>special://skin/tvpmc/news/05news.jpg</texturenofocus>
            </control>
            <control type="button" id="9006">
                <width>1920</width>
                <height>1080</height>
                <onfocus>AlarmClock(SwitchRight,Action(Right),00:05,silent)</onfocus>
                <onclick>Action(Right)</onclick>
                <texturefocus>special://skin/tvpmc/news/06news.jpg</texturefocus>
                <texturenofocus>special://skin/tvpmc/news/06news.jpg</texturenofocus>
            </control>
            <control type="button" id="9007">
                <width>1920</width>
                <height>1080</height>
                <onfocus>AlarmClock(SwitchRight,Action(Right),00:05,silent)</onfocus>
                <onclick>Action(Right)</onclick>
                <texturefocus>special://skin/tvpmc/news/07news.jpg</texturefocus>
                <texturenofocus>special://skin/tvpmc/news/07news.jpg</texturenofocus>
            </control>
            <control type="button" id="9008">
                <width>1920</width>
                <height>1080</height>
                <onfocus>AlarmClock(SwitchRight,Action(Right),00:05,silent)</onfocus>
                <onclick>Action(Right)</onclick>
                <texturefocus>special://skin/tvpmc/news/08news.jpg</texturefocus>
                <texturenofocus>special://skin/tvpmc/news/08news.jpg</texturenofocus>
            </control>
            <control type="button" id="9009">
                <width>1920</width>
                <height>1080</height>
                <onfocus>AlarmClock(SwitchRight,Action(Right),00:05,silent)</onfocus>
                <onclick>Action(Right)</onclick>
                <texturefocus>special://skin/tvpmc/news/09news.jpg</texturefocus>
                <texturenofocus>special://skin/tvpmc/news/09news.jpg</texturenofocus>
            </control>
            <control type="button" id="9010">
                <width>1920</width>
                <height>1080</height>
                <onfocus>AlarmClock(SwitchRight,Action(Right),00:05,silent)</onfocus>
                <onclick>Action(Right)</onclick>
                <texturefocus>special://skin/tvpmc/news/10news.jpg</texturefocus>
                <texturenofocus>special://skin/tvpmc/news/10news.jpg</texturenofocus>
                <onright>Close</onright>
            </control>
        </control>
        <control type="button">
            <width>96</width>
            <height>96</height>
            <texturenofocus colordiffuse="bfffffff" flipx="true">common/bigarrow.png</texturenofocus>
            <texturefocus colordiffuse="$VAR[HighlightColor]" flipx="true">common/bigarrow.png</texturefocus>
            <centertop>54%</centertop>
            <left>20</left>
            <visible>Container(9000).HasPrevious</visible>
            <onclick>Action(Left)</onclick>
        </control>
        <control type="button">
            <width>96</width>
            <height>96</height>
            <texturenofocus colordiffuse="bfffffff">common/bigarrow.png</texturenofocus>
            <texturefocus colordiffuse="$VAR[HighlightColor]">common/bigarrow.png</texturefocus>
            <centertop>54%</centertop>
            <right>20</right>
            <visible>Container(9000).HasNext</visible>
            <onclick>Action(Right)</onclick>
        </control>
  </controls>
</window>
